chromecast_volumecontrol/__init__.py
chromecast_volumecontrol/control_chromecasts.py
chromecast_volumecontrol/flask_endpoint.py
chromecast_volumecontrol/gui.py
chromecast_volumecontrol/ico/cc.png
chromecast_volumecontrol-0.0.8.data/scripts/cc_volumecontrol
chromecast_volumecontrol-0.0.8.dist-info/LICENSE
chromecast_volumecontrol-0.0.8.dist-info/METADATA
chromecast_volumecontrol-0.0.8.dist-info/WHEEL
chromecast_volumecontrol-0.0.8.dist-info/top_level.txt
chromecast_volumecontrol-0.0.8.dist-info/RECORD
