Metadata-Version: 2.1
Name: chromecast-volumecontrol
Version: 0.0.8
Summary: Control Chromecast Volume
Home-page: https://github.com/merklel/chromecast-frontend
Author: Lukas Merkle
Author-email: lukas.merkle@live.de
License: UNKNOWN
Platform: UNKNOWN
Classifier: Programming Language :: Python :: 3
Classifier: License :: OSI Approved :: MIT License
Classifier: Operating System :: OS Independent
Requires-Python: >=3.6
License-File: LICENSE
Requires-Dist: pychromecast
